datasette_uptime/__init__.py
datasette_uptime-0.1.1.dist-info/LICENSE
datasette_uptime-0.1.1.dist-info/METADATA
datasette_uptime-0.1.1.dist-info/WHEEL
datasette_uptime-0.1.1.dist-info/entry_points.txt
datasette_uptime-0.1.1.dist-info/top_level.txt
datasette_uptime-0.1.1.dist-info/RECORD
