Metadata-Version: 2.1
Name: datasette-uptime
Version: 0.1.1
Summary: Datasette plugin showing uptime at /-/uptime
Author: Simon Willison
License: Apache-2.0
Project-URL: Homepage, https://github.com/datasette/datasette-uptime
Project-URL: Changelog, https://github.com/datasette/datasette-uptime/releases
Project-URL: Issues, https://github.com/datasette/datasette-uptime/issues
Project-URL: CI, https://github.com/datasette/datasette-uptime/actions
Classifier: Framework :: Datasette
Classifier: License :: OSI Approved :: Apache Software License
Requires-Python: >=3.8
License-File: LICENSE
Requires-Dist: datasette
Provides-Extra: test
Requires-Dist: pytest ; extra == 'test'
Requires-Dist: pytest-asyncio ; extra == 'test'
